{
    "version": "1.8",
    "description": "LiveSplit. Timer for speedrunners",
    "homepage": "https://livesplit.org",
    "license": {
        "identifier": "MIT",
        "url": "https://github.com/LiveSplit/LiveSplit/blob/master/LICENSE"
    },
    "url": "https://github.com/LiveSplit/LiveSplit/releases/download/1.8/LiveSplit_1.8.zip",
    "hash": "19a1424af845a22593faee1b661d6ed81eda4cc9ca706ac49dba3121c578b29e",
    "bin": "LiveSplit.exe",
    "shortcuts": [
        [
            "LiveSplit.exe",
            "LiveSplit"
        ]
    ],
    "checkver": {
        "github": "https://github.com/LiveSplit/LiveSplit"
    },
    "autoupdate": {
        "url": "https://github.com/LiveSplit/LiveSplit/releases/download/$version/LiveSplit_$version.zip"
    }
}
