{
    "version": "15.2.20190201",
    "description": "Visual Paradigm Enterprise Edition. UML CASE Tool supporting UML 2, SysML and Business Process Modeling Notation from the Object Management Group.",
    "homepage": "https://www.visual-paradigm.com/",
    "license": {
        "identifier": "Trialware",
        "url": "https://www.visual-paradigm.com/product/licenseagreement.jsp?product=vp&edition=ee"
    },
    "architecture": {
        "64bit": {
            "url": "https://uk4.visual-paradigm.com/visual-paradigm/vp15.2/20190201/Visual_Paradigm_15_2_20190201_Win64_InstallFree.zip",
            "hash": "2f22d7c66258a8bafc493c582704cb435016971c4ce4960e36f8c124c4e4c21d"
        },
        "32bit": {
            "url": "https://uk4.visual-paradigm.com/visual-paradigm/vp15.2/20190201/Visual_Paradigm_15_2_20190201_Win32_InstallFree.zip",
            "hash": "4cd7b9b3758c9586e78a6a5e87fbd802b93520a10b3c9a7896d689125e77222a"
        }
    },
    "extract_dir": "Visual Paradigm 15.2",
    "shortcuts": [
        [
            "Visual Paradigm.exe",
            "Visual Paradigm"
        ]
    ],
    "checkver": {
        "url": "https://www.visual-paradigm.com/download/",
        "regex": "Version:\\s*(?<ver>[\\d\\.]+).*Build number:\\s*(?<build>(\\d{8}))",
        "replace": "${ver}.${build}"
    },
    "autoupdate": {
        "architecture": {
            "64bit": {
                "url": "https://uk4.visual-paradigm.com/visual-paradigm/vp$matchVer/$matchBuild/Visual_Paradigm_$underscoreVersion_Win64_InstallFree.zip"
            },
            "32bit": {
                "url": "https://uk4.visual-paradigm.com/visual-paradigm/vp$matchVer/$matchBuild/Visual_Paradigm_$underscoreVersion_Win32_InstallFree.zip"
            }
        },
        "hash": {
            "url": "https://uk4.visual-paradigm.com/visual-paradigm/vp$matchVer/$matchBuild/checksum.html",
            "regex": "$basename\\s*</td>\\s*<td>\\s*sha256: ($sha256)"
        },
        "extract_dir": "Visual Paradigm $matchVer"
    }
}
