{
    "version": "0.084",
    "description": "MakePartitionImage. Converts a bootable payload file (or USB drive partition) into a partition image (.imgPTN) file.",
    "homepage": "http://www.easy2boot.com/download/mpi-pack/",
    "url": "http://files.easy2boot.com/200003289-1749a18440/MPI_Tool_Pack_Plus_CloverLite_084.zip",
    "hash": "b1378ea2a06631e482aca306cf2449e2bbd6c8d7505ca6f3199e97516acdf4e3",
    "extract_dir": "MPI_Tool_Pack_Plus_CloverLite_084",
    "checkver": {
        "re": "a href=\".*easy2boot.com/(?<cosi>\\d+-\\w+)/.*>MPI_Tool_Pack_Plus_CloverLite_(?<ver>[\\d+\\.]+) \\([\\d+-]+\\)",
        "replace": "${ver}"
    },
    "autoupdate": {
        "url": "http://files.easy2boot.com/$matchCosi/MPI_Tool_Pack_Plus_CloverLite_$minorVersion.zip",
        "extract_dir": "MPI_Tool_Pack_Plus_CloverLite_$minorVersion"
    }
}
