{
    "version": "56.0.3051.88",
    "description": "Opera. Fast, secure, easy-to-use browser.",
    "homepage": "https://www.opera.com/",
    "license": {
        "identifier": "Freeware"
    },
    "architecture": {
        "64bit": {
            "url": "https://download1.operacdn.com/pub/opera/desktop/56.0.3051.88/win/Opera_56.0.3051.88_Setup_x64.exe",
            "hash": "61139610defe75a47c8568f8bd70e0dd2212df23d715bbdec57f1e4181eaee9a"
        },
        "32bit": {
            "url": "https://download1.operacdn.com/pub/opera/desktop/56.0.3051.88/win/Opera_56.0.3051.88_Setup.exe",
            "hash": "79f574d867067b75f599b75f51c33224a83ef67dec360d8a7ad08b9b70f1bfc7"
        }
    },
    "installer": {
        "args": [
            "/silent",
            "/installfolder=\"$dir\"",
            "/copyonly=1",
            "/desktopshortcut=0",
            "/startmenushortcut=0",
            "/quicklaunchshortcut=0",
            "/enable-stats=0",
            "/enable-installer-stats=0",
            "/launchbrowser=0"
        ]
    },
    "persist": "profile",
    "shortcuts": [
        [
            "launcher.exe",
            "Opera"
        ]
    ],
    "checkver": {
        "url": "http://get.opera.com/ftp/pub/opera/desktop/",
        "regex": "([\\d+\\.]+)/",
        "reverse": true
    },
    "autoupdate": {
        "architecture": {
            "64bit": {
                "url": "https://download1.operacdn.com/pub/opera/desktop/$version/win/Opera_$version_Setup_x64.exe"
            },
            "32bit": {
                "url": "https://download1.operacdn.com/pub/opera/desktop/$version/win/Opera_$version_Setup.exe"
            }
        }
    }
}
