{
    "version": "0.0.5-7428",
    "description": "RPCS3. PS3 emulator/debugger.",
    "homepage": "https://rpcs3.net/",
    "license": {
        "identifier": "GPL-2.0",
        "url": "https://github.com/RPCS3/rpcs3/blob/master/LICENSE"
    },
    "notes": [
        "Install firmware via 'File -> Install firmware'.",
        "    Latest firmware file ('PS3UPDAT.PUP') is located inside app directory ('$dir').",
        "HOW TO INSTALL GAME:",
        "1.   Download games from 'http://psndl.net/packages'",
        "1.1.       Both files ('Rap', 'Package') are needed",
        "2.   Install via 'File -> Install .pkg'",
        "3.   Copy RAP file and paste it into '$dir\\dev_hdd0\\home\\00000001\\exdata'",
        "4.   Enjoy the game <3"
    ],
    "depends": "vcredist2015",
    "architecture": {
        "64bit": {
            "url": [
                "https://github.com/RPCS3/rpcs3-binaries-win/releases/download/build-cc846eb67030fd56a72c0e2ec5709a4b79c7edc3/rpcs3-v0.0.5-7428-cc846eb6_win64.7z",
                "http://dus01.ps3.update.playstation.net/update/ps3/image/us/2017_1113_152d950c365ede4130c53ceb18dcd43b/PS3UPDAT.PUP"
            ],
            "hash": [
                "cc983a10b474dd3fc3ecc6bc61c8add24962ecf6342b68f05382bf7cc74ce721",
                "a70669bc35a5d688c94f5db8e1eb4110295b1b076ccc3c8e4a7e9ee397a6ca41"
            ]
        }
    },
    "installer": {
        "script": [
            "$file = 'GuiConfigs\\CurrentSettings.ini'",
            "if (!(Test-Path \"$persist_dir\\$file\")) {",
            "    Write-Host 'File' $file 'does not exists. Creating.' -f Yellow",
            "    $outfile = \"$dir\\$file\"",
            "    New-Item $outFile -Type File -Force | Out-Null",
            "    $CONT = @('[Meta]', 'currentStylesheet=Darker Style by TheMitoSan')",
            "    Set-Content $outFile ($CONT -join \"`r`n\") -Encoding Ascii",
            "}"
        ]
    },
    "persist": [
        "dev_hdd0",
        "GuiConfigs",
        "PS3UPDAT.PUP"
    ],
    "shortcuts": [
        [
            "rpcs3.exe",
            "RPCS3"
        ]
    ],
    "checkver": {
        "url": "https://github.com/RPCS3/rpcs3-binaries-win/releases/latest/",
        "regex": "<a href=\".*/build-(?<commit>(?<cosi>\\w{8})\\w{32})/rpcs3-v(?<mainVersion>[\\d+\\.]+-\\d{4})",
        "replace": "${mainVersion}"
    },
    "autoupdate": {
        "architecture": {
            "64bit": {
                "url": "https://github.com/RPCS3/rpcs3-binaries-win/releases/download/build-$matchCommit/rpcs3-v$version-$matchCosi_win64.7z",
                "hash": {
                    "url": "https://github.com/RPCS3/rpcs3-binaries-win/releases/latest/",
                    "find": "<p>([A-Fa-f\\d]{64});"
                }
            }
        }
    }
}
