{
    "version": "nightly",
    "description": "Microsoft Visual Studio Code - Insiders. New type of tool that combines the simplicity of a code editor with what developers need for their core edit-build-debug cycle.",
    "homepage": "https://code.visualstudio.com/insiders",
    "license": {
        "identifier": "MIT",
        "url": "https://code.visualstudio.com/license/insiders"
    },
    "notes": "When there is vscode update available run 'scoop update vscode-insiders -f'",
    "architecture": {
        "64bit": {
            "url": [
                "https://vscode-update.azurewebsites.net/latest/win32-x64-archive/insider#/cosi.zip",
                "https://raw.githubusercontent.com/lukesampson/scoop-extras/master/scripts/vscode-install-context.reg",
                "https://raw.githubusercontent.com/lukesampson/scoop-extras/master/scripts/vscode-uninstall-context.reg"
            ],
            "hash": [
                "dc2a228061ce356a4dcecce1f57adfbc07574f979a46979f789cca029f9102b8",
                "c6c3d03e23e24a6ed4373eff4e876f33671bcb2ffc1a3a552f5df20671639bc6",
                "3c4844429e002cfa7430aaea6db8bf761b2d2b466d62771df8d74ba962ee9d11"
            ]
        },
        "32bit": {
            "url": [
                "https://vscode-update.azurewebsites.net/latest/win32-archive/insider#/cosi.zip",
                "https://raw.githubusercontent.com/lukesampson/scoop-extras/master/scripts/vscode-install-context.reg",
                "https://raw.githubusercontent.com/lukesampson/scoop-extras/master/scripts/vscode-uninstall-context.reg"
            ],
            "hash": [
                "e9a147437543b9c21474df819be7fbced3773445313f59b635bdf1837b054b6f",
                "c6c3d03e23e24a6ed4373eff4e876f33671bcb2ffc1a3a552f5df20671639bc6",
                "3c4844429e002cfa7430aaea6db8bf761b2d2b466d62771df8d74ba962ee9d11"
            ]
        }
    },
    "post_install": [
        "$port = \"$dir\\data\"",
        "    # Create data folder",
        "if(!(Test-Path \"$persist_dir\\data\")) { ",
        "    Write-Host 'No user data folder exists' -f Yellow",
        "    New-Item \"$port\\tmp\", \"$port\\user-data\", \"$port\\extensions\" -Force -Type Directory | Out-Null",
        "}",
        "    # Create install context file",
        "$codepath = \"$dir\\Code - Insiders.exe\".Replace('\\', '\\\\')",
        "$content = Get-Content \"$dir\\vscode-install-context.reg\"",
        "$content = $content.Replace('$code', $codepath)",
        "$content = $content.Replace('&Code', 'Code &Insiders')",
        "Set-Content \"$dir\\vscode-install-context.reg\" $content",
        "    # Create uninstall context file",
        "$content = Get-Content \"$dir\\vscode-uninstall-context.reg\"",
        "$content = $content.Replace('&Code', 'Code &Insiders')",
        "Set-Content \"$dir\\vscode-uninstall-context.reg\" $content",
        "    # Apply context automatically",
        "regedit /s \"$dir\\vscode-install-context.reg\""
    ],
    "uninstaller": {
        "script": [
            "    # Uninstall context menu",
            "regedit /s \"$dir\\vscode-uninstall-context.reg\""
        ]
    },
    "persist": "data",
    "bin": [
        "bin\\code-insiders.cmd",
        "Code - Insiders.exe"
    ],
    "shortcuts": [
        [
            "Code - Insiders.exe",
            "Visual Studio Code - Insiders"
        ]
    ],
    "checkver": {
        "url": "https://code.visualstudio.com/sha?build=insider",
        "jp": "$.products[?(@.platform.os == 'win32-x64-archive')].name"
    },
    "autoupdate": {
        "architecture": {
            "64bit": {
                "url": "https://vscode-update.azurewebsites.net/$version/win32-x64-archive/insider#cosi.zip",
                "hash": {
                    "url": "https://code.visualstudio.com/sha?build=insider",
                    "jp": "$.products[?(@.platform.os == 'win32-x64-archive')].sha256hash"
                }
            },
            "32bit": {
                "url": "https://vscode-update.azurewebsites.net/$version/win32-archive/insider#cosi.zip",
                "hash": {
                    "url": "https://code.visualstudio.com/sha?build=insider",
                    "jp": "$.products[?(@.platform.os == 'win32-archive')].sha256hash"
                }
            }
        }
    }
}
