{
    "version": "10.1.3.759",
    "description": "Wise Disk Cleaner. Clean junks of Browsers, remove junk and useless files of Windows and Defragment disk.",
    "homepage": "https://www.wisecleaner.com/wise-disk-cleaner.html",
    "license": {
        "identifier": "Freeware"
    },
    "url": "http://downloads.wisecleaner.com/soft/WDCFree.zip",
    "hash": "9243d1c761a899a91fcb9794eecfa5e02e279fb9780c627edc85e6148f5f1c5f",
    "extract_dir": "Wise Disk Cleaner",
    "installer": {
        "script": [
            "$file = 'config.ini'",
            "$CONT = (Get-Content \"$dir\\config.ini\")",
            "$CONT = $CONT -replace 'checkNewVer=1', 'checkNewVer=0'",
            "Set-Content \"$dir\\$file\" $CONT -Encoding Ascii"
        ]
    },
    "persist": [
        "config.ini",
        "DefragOptions.ini"
    ],
    "shortcuts": [
        [
            "WiseDiskCleaner.exe",
            "Wise Disk Cleaner"
        ]
    ],
    "checkver": "version: ([\\d\\.]+)",
    "autoupdate": {
        "url": "http://downloads.wisecleaner.com/soft/WDCFree.zip"
    }
}
