{
    "##": [
        "Application is working correctly, but some services need to be initialized.",
        "Explore if it's possible to do it after install.",
        "Otherwise, Install it."
    ],
    "version": "3.22.74",
    "description": "Corsair's iCue. Connects all your compatible products together in a single interface, giving you complete control of everything from RGB lighting and effects to fan speeds and temperature monitoring.",
    "homepage": "https://www.corsair.com/us/en/icue",
    "url": "http://softwaredownloads.corsair.com/Files/CUE/iCUESetup_3.22.74_release.msi",
    "hash": "368482fe13936dac87adea9cbe538f29a69e8aa8a36739edafcff709d2c06327",
    "extract_dir": "Corsair\\iCue",
    "shortcuts": [
        [
            "iCue.exe",
            "iCUE"
        ]
    ],
    "checkver": {
        "url": "https://www.corsair.com/eu/en/downloads/",
        "regex": "CORSAIR iCUE v([\\d\\.]+)"
    },
    "autoupdate": {
        "url": "http://softwaredownloads.corsair.com/Files/CUE/iCUESetup_$version_release.msi"
    }
}
