{
    "version": "6.6.0.0",
    "description": "Nox App Player. The perfect Android emulator to play mobile games on PC.",
    "homepage": "https://www.bignox.com/",
    "url": "https://www.bignox.com/en/download/fullPackage#/cosi.exe",
    "hash": "39b1baa7c11a2bc2855a6c611b473160b75caa6d84aee45f4c6e50e57808b84c",
    "installer": {
        "args": [
            "/S",
            "/D=$dir"
        ]
    },
    "shortcuts": [
        [
            "Nox.exe",
            "Nox App Player"
        ]
    ],
    "checkver": "Version ([\\d\\.]+)",
    "autoupdate": {
        "url": "https://www.bignox.com/en/download/fullPackage#/cosi.exe"
    }
}
